<?xml version="1.0" encoding="UTF-8"?>
<!DOCTYPE suite SYSTEM "https://testng.org/testng-1.0.dtd">
<suite name="Suite13">

  <test thread-count="5" name="Membersummary-various-cases-suchas-avtar,uploadposture-bodyscan-vo2-result">
    <classes>    
      <class name="cuesz.membersummarytest.advocate.Case31_MS_Avtarclicktest"/>
	  <class name="cuesz.membersummarytest.advocate.Case33_MS_Uploadposturetest"/>
	  <class name="cuesz.membersummarytest.advocate.Case71_MS_bodyscancomparetest"/>
	  <class name="cuesz.membersummarytest.advocate.Case77_MS_uplaodtonnage_Physiologicaltest"/>
	  <class name="cuesz.membersummarytest.advocate.Case78_MS_uplaodperformancesummarytest"/>
	  <class name="cuesz.membersummarytest.advocate.Case80_MS_Sessionoutcometest"/>
	  <class name="cuesz.membersummarytest.advocate.Case81_MS_Sleeptimetest"/>
	 <class name="cuesz.membersummarytest.advocate.Case32_MS_Bodyscanresulttest"/>
     <class name="cuesz.membersummarytest.advocate.Case34_01_MS_VO2assigntomembertest"/>
	 <class name="cuesz.membersummarytest.advocate.Case34_MS_VO2Resulttest"/>

    </classes>
  </test> <!-- Test -->
</suite> <!-- Suite -->